{
  "krk-color-ink-600": "#382f5e",
  "krk-color-ink-700": "#2a2348",
  "krk-color-ink-750": "#221c40",
  "krk-color-ink-800": "#1b1633",
  "krk-color-ink-850": "#141026",
  "krk-color-ink-900": "#0e0b1c",
  "krk-color-ink-950": "#0a0714",
  "krk-color-fog-50": "#f5f4fb",
  "krk-color-fog-200": "#dad8e8",
  "krk-color-fog-400": "#a7a2c0",
  "krk-color-fog-500": "#7e7a98",
  "krk-color-fog-600": "#5c5878",
  "krk-color-violet-300": "#c4b5fd",
  "krk-color-violet-400": "#a78bfa",
  "krk-color-violet-500": "#8b5cf6",
  "krk-color-violet-600": "#7c3aed",
  "krk-color-violet-700": "#6d28d9",
  "krk-color-violet-tint": "#1c1640",
  "krk-color-blue-400": "#818cf8",
  "krk-color-blue-500": "#6366f1",
  "krk-color-blue-tint": "#141a3a",
  "krk-color-green-500": "#34d399",
  "krk-color-green-tint": "#0e2a22",
  "krk-color-amber-500": "#f5b544",
  "krk-color-amber-tint": "#2a2110",
  "krk-color-rose-500": "#fb7185",
  "krk-color-rose-tint": "#2e1524",
  "krk-color-pure-white": "#ffffff",
  "krk-color-pure-black": "#000000",
  "krk-glow-accent-soft": "0 0 24px rgba(139,92,246,0.25)",
  "krk-glow-accent": "0 0 40px rgba(139,92,246,0.40)",
  "krk-glow-accent-strong": "0 0 64px rgba(139,92,246,0.55)",
  "krk-glow-blue": "0 0 40px rgba(99,102,241,0.35)",
  "krk-elevation-0": "none",
  "krk-elevation-1": "0 1px 2px rgba(0,0,0,0.35), 0 1px 3px rgba(0,0,0,0.25)",
  "krk-elevation-2": "0 4px 12px rgba(0,0,0,0.40), 0 2px 4px rgba(0,0,0,0.30)",
  "krk-elevation-3": "0 12px 32px rgba(0,0,0,0.50), 0 4px 8px rgba(0,0,0,0.35)",
  "krk-duration-instant": "0ms",
  "krk-duration-fast": "120ms",
  "krk-duration-base": "200ms",
  "krk-duration-slow": "320ms",
  "krk-easing-standard": "cubic-bezier(0.2, 0, 0, 1)",
  "krk-easing-entrance": "cubic-bezier(0, 0, 0, 1)",
  "krk-easing-exit": "cubic-bezier(0.3, 0, 1, 1)",
  "krk-space-0": "0px",
  "krk-space-1": "4px",
  "krk-space-2": "8px",
  "krk-space-3": "12px",
  "krk-space-4": "16px",
  "krk-space-5": "20px",
  "krk-space-6": "24px",
  "krk-space-8": "32px",
  "krk-space-10": "40px",
  "krk-space-12": "48px",
  "krk-space-16": "64px",
  "krk-space-20": "80px",
  "krk-radius-sm": "8px",
  "krk-radius-md": "10px",
  "krk-radius-lg": "14px",
  "krk-radius-xl": "16px",
  "krk-radius-pill": "999px",
  "krk-border-hairline": "1px",
  "krk-border-strong": "2px",
  "krk-breakpoint-sm": "540px",
  "krk-breakpoint-md": "768px",
  "krk-breakpoint-lg": "1024px",
  "krk-breakpoint-xl": "1280px",
  "krk-z-index-base": 0,
  "krk-z-index-dropdown": 1000,
  "krk-z-index-sticky": 1100,
  "krk-z-index-overlay": 1200,
  "krk-z-index-modal": 1300,
  "krk-z-index-toast": 1400,
  "krk-surface-page": "#0a0714",
  "krk-surface-base": "#0e0b1c",
  "krk-surface-raised": "#141026",
  "krk-surface-overlay": "#1b1633",
  "krk-surface-field": "#141026",
  "krk-text-primary": "#f5f4fb",
  "krk-text-secondary": "#a7a2c0",
  "krk-text-muted": "#7e7a98",
  "krk-text-on-accent": "#ffffff",
  "krk-line-default": "#2a2348",
  "krk-line-strong": "#382f5e",
  "krk-accent-default": "#8b5cf6",
  "krk-accent-hover": "#a78bfa",
  "krk-accent-pressed": "#7c3aed",
  "krk-accent-text": "#c4b5fd",
  "krk-accent-tint": "#1c1640",
  "krk-accent-secondary": "#6366f1",
  "krk-accent-secondary-text": "#818cf8",
  "krk-status-ok": "#34d399",
  "krk-status-ok-tint": "#0e2a22",
  "krk-status-warning": "#f5b544",
  "krk-status-warning-tint": "#2a2110",
  "krk-status-danger": "#fb7185",
  "krk-status-danger-tint": "#2e1524",
  "krk-focus-ring": "#8b5cf6",
  "krk-font-family-sans": "-apple-system, \"Segoe UI\", Helvetica, Arial, sans-serif",
  "krk-font-family-mono": "ui-monospace, SFMono-Regular, Menlo, monospace",
  "krk-font-weight-regular": 400,
  "krk-font-weight-medium": 500,
  "krk-font-weight-semibold": 600,
  "krk-font-weight-bold": 700,
  "krk-font-size-xs": "12px",
  "krk-font-size-sm": "13px",
  "krk-font-size-base": "14px",
  "krk-font-size-md": "15px",
  "krk-font-size-lg": "18px",
  "krk-font-size-xl": "22px",
  "krk-font-size-2xl": "26px",
  "krk-font-size-3xl": "32px",
  "krk-font-size-4xl": "42px",
  "krk-font-size-5xl": "56px",
  "krk-line-height-tight": 1.25,
  "krk-line-height-normal": 1.5,
  "krk-line-height-relaxed": 1.6,
  "krk-letter-spacing-eyebrow": "0.12em",
  "krk-letter-spacing-tight": "-0.01em"
}
